rsa_crypto_python/__init__.py
rsa_crypto_python/rsa_crypto_python.py
rsa_crypto_python-2.0.4.dist-info/LICENSE
rsa_crypto_python-2.0.4.dist-info/METADATA
rsa_crypto_python-2.0.4.dist-info/WHEEL
rsa_crypto_python-2.0.4.dist-info/top_level.txt
rsa_crypto_python-2.0.4.dist-info/RECORD
