Metadata-Version: 2.1
Name: rsa-crypto-python
Version: 2.0.4
Summary: A package that implements assymetric encryption and description using rsa
Author-email: "Ukweh Everest(Exrelativity)" <exrelativity@github.com>
Project-URL: Homepage, https://github.com/relativity-codes/rsa-crypto-python.git
Project-URL: Issues, https://github.com/relativity-codes/rsa-crypto-python/issues
Classifier: Programming Language :: Python :: 3
Classifier: License :: OSI Approved :: MIT License
Classifier: Operating System :: OS Independent
Requires-Python: >=3.8
License-File: LICENSE
